{
  "unversionedId": "api/class-websocketframe",
  "id": "version-1.23/api/class-websocketframe",
  "title": "WebSocketFrame",
  "description": "The WebSocketFrame] class represents frames sent over [WebSocket] connections in the page. Frame payload is returned by either [WebSocketFrame.Text or WebSocketFrame.Binary method depending on the its type.",
  "source": "@site/versioned_docs/version-1.23/api/class-websocketframe.mdx",
  "sourceDirName": "api",
  "slug": "/api/class-websocketframe",
  "permalink": "/dotnet/docs/api/class-websocketframe",
  "tags": [],
  "version": "1.23",
  "frontMatter": {
    "id": "class-websocketframe",
    "title": "WebSocketFrame"
  },
  "sidebar": "api",
  "previous": {
    "title": "WebSocket",
    "permalink": "/dotnet/docs/api/class-websocket"
  },
  "next": {
    "title": "Worker",
    "permalink": "/dotnet/docs/api/class-worker"
  }
}